<?xml version="1.0" encoding="utf-8"?>
<Deployment xmlns="http://schemas.microsoft.com/windowsphone/2014/deployment" AppPlatformVersion="8.1">
  <DefaultLanguage xmlns="" code="zh-CN" />
  <App xmlns="" ProductID="{993e4e45-ae65-45f4-9269-fa0a8494bcd9}" Title="饭窗" RuntimeType="Silverlight" Version="1.0.0.0" Genre="apps.normal" Author="iEle" Description="Fanfou Client for Windows Phone" Publisher="FanfouWP" PublisherID="{e5bfe9c9-2238-41e4-a9a7-f9e005685df3}">
    <IconPath IsRelative="true" IsResource="false">Assets\ApplicationIcon.png</IconPath>
    <Capabilities>
      <Capability Name="ID_CAP_WEBBROWSERCOMPONENT" />
      <Capability Name="ID_CAP_REMOVABLE_STORAGE" />
      <Capability Name="ID_CAP_IDENTITY_DEVICE" />
      <Capability Name="ID_CAP_IDENTITY_USER" />
      <Capability Name="ID_CAP_LOCATION" />
      <Capability Name="ID_CAP_NETWORKING" />
      <Capability Name="ID_CAP_SENSORS" />
      <Capability Name="ID_CAP_MEDIALIB_PHOTO" />
      <Capability Name="ID_CAP_MAP" />
      <Capability Name="ID_CAP_ISV_CAMERA" />
      <Capability Name="ID_CAP_MICROPHONE" />
      <Capability Name="ID_CAP_SPEECH_RECOGNITION" />
    </Capabilities>
    <Tasks>
      <DefaultTask Name="_default" NavigationPage="MainPage.xaml" />
    </Tasks>
    <Tokens>
      <PrimaryToken TokenID="FanfouWPToken" TaskName="_default">
        <TemplateIconic>
          <SmallImageURI IsRelative="true" IsResource="false">Assets\icon-small.png</SmallImageURI>
          <Count>0</Count>
          <IconImageURI IsRelative="true" IsResource="false">Assets\icon-medium.png</IconImageURI>
          <Title>饭窗</Title>
          <Message></Message>
          <BackgroundColor></BackgroundColor>
          <HasLarge>True</HasLarge>
          <LargeContent1></LargeContent1>
          <LargeContent2></LargeContent2>
          <LargeContent3></LargeContent3>
          <DeviceLockImageURI IsRelative="true" IsResource="false"></DeviceLockImageURI>
        </TemplateIconic>
      </PrimaryToken>
    </Tokens>
    <ScreenResolutions>
      <ScreenResolution Name="ID_RESOLUTION_WVGA" />
      <ScreenResolution Name="ID_RESOLUTION_WXGA" />
      <ScreenResolution Name="ID_RESOLUTION_HD720P" />
    </ScreenResolutions>
  </App>
</Deployment>